HFResourceScanner/__init__.py
HFResourceScanner/scanner.py
HFResourceScanner/test.py
HFResourceScanner/utils.py
HFResourceScanner-0.1.2.dist-info/LICENSE
HFResourceScanner-0.1.2.dist-info/METADATA
HFResourceScanner-0.1.2.dist-info/WHEEL
HFResourceScanner-0.1.2.dist-info/top_level.txt
HFResourceScanner-0.1.2.dist-info/RECORD
