Metadata-Version: 2.2
Name: HFResourceScanner
Version: 0.1.2
Summary: Scan resources used during training using HFTrainer
Author-email: Chander Govindarajan <mail@chandergovind.org>
License: Apache-2.0
Project-URL: Homepage, https://github.com/foundation-model-stack/hf-resource-scanner
Project-URL: Issues, https://github.com/foundation-model-stack/hf-resource-scanner/issues
Classifier: Programming Language :: Python :: 3
Classifier: License :: OSI Approved :: Apache Software License
Classifier: Operating System :: OS Independent
Requires-Python: >=3.8
License-File: LICENSE
Requires-Dist: torch
Requires-Dist: transformers
Requires-Dist: accelerate
Requires-Dist: peft
